{
    "fluentMethods": true,
    "relationships": [],
    "fields": [
        {
            "fieldName": "countryName",
            "fieldType": "String"
        },
        {
            "fieldName": "locationGoogleMaps",
            "fieldType": "String"
        },
        {
            "fieldName": "latitude",
            "fieldType": "Double"
        },
        {
            "fieldName": "logitude",
            "fieldType": "Double"
        }
    ],
    "changelogDate": "20171104120018",
    "entityTableName": "country",
    "dto": "no",
    "pagination": "no",
    "service": "no",
    "jpaMetamodelFiltering": false
}